<?xml version="1.0" encoding="utf-8"?>
<dataset>
    <table name="tb_sys_user">
    <column>id</column>
    <column>version</column>
    <column>username</column>
    <column>password</column>
    <column>password_hint</column>
    <column>first_name</column>
    <column>last_name</column>
    <column>email</column>
    <column>phone_number</column>
    <column>website</column>
    <column>address</column>
    <column>city</column>
    <column>province</column>
    <column>country</column>
    <column>postal_code</column>
    <column>account_enabled</column>
    <column>account_expired</column>
    <column>account_locked</column>
    <column>credentials_expired</column>
    <row>
      <value>1</value>
      <value>3</value>
      <value>admin</value>
      <value>d033e22ae348aeb5660fc2140aec35850c4da997</value>
      <value><![CDATA[Not a female kitty.]]></value>
      <value>张</value>
      <value>丽</value>
      <value>matt@raibledesigns.com</value>
      <value/>
      <value>http://raibledesigns.com</value>
      <value/>
      <value>Denver</value>
      <value>CO</value>
      <value>US</value>
      <value>80210</value>
      <value>1</value>
      <value>0</value>
      <value>0</value>
      <value>0</value>
    </row>
    <row>
      <value>2</value>
      <value>2</value>
      <value>guest</value>
      <value>d0b29dad371307a38b8b55be3676c3d8d85090a6</value>
      <value><![CDATA[A male kitty.]]></value>
      <value>赵</value>
      <value>传</value>
      <value>matt_raible@yahoo.com</value>
      <value/>
      <value>http://jakarta.apache.org/tomcat</value>
      <value/>
      <value>Denver</value>
      <value>CO</value>
      <value>US</value>
      <value>80210</value>
      <value>1</value>
      <value>0</value>
      <value>0</value>
      <value>0</value>
    </row>
    <row>
      <value>3</value>
      <value>3</value>
      <value>test</value>
      <value>b2c2a9ca41e220a80237ea3f484b92af0b7c7223</value>
      <value/>
      <value>李</value>
      <value>想</value>
      <value>a@b.com</value>
      <value/>
      <value/>
      <value/>
      <value/>
      <value/>
      <value/>
      <value/>
      <value>1</value>
      <value>0</value>
      <value>0</value>
      <value>0</value>
    </row>
    <row>
      <value>4</value>
      <value>2</value>
      <value>soa</value>
      <value>89235a5c7afee61a8e03161ce64db1edcf0ec8dc</value>
      <value/>
      <value>曾</value>
      <value>嵘</value>
      <value>soa@hotmail.com</value>
      <value>69333456</value>
      <value/>
      <value/>
      <value/>
      <value/>
      <value/>
      <value/>
      <value>1</value>
      <value>0</value>
      <value>0</value>
      <value>0</value>
    </row>
    <row>
      <value>5</value>
      <value>2</value>
      <value>zhangzhen</value>
      <value>89235a5c7afee61a8e03161ce64db1edcf0ec8dc</value>
      <value/>
      <value>张</value>
      <value>臻</value>
      <value>zhang@hotmai.com</value>
      <value>69333626</value>
      <value/>
      <value/>
      <value/>
      <value/>
      <value/>
      <value/>
      <value>1</value>
      <value>0</value>
      <value>0</value>
      <value>0</value>
    </row>
    <row>
      <value>6</value>
      <value>3</value>
      <value>yangguang</value>
      <value>2e259ed445d779e786f14861fe624eb39132f591</value>
      <value/>
      <value>杨</value>
      <value>海光</value>
      <value>yang@hotmail.com</value>
      <value/>
      <value/>
      <value/>
      <value/>
      <value/>
      <value/>
      <value/>
      <value>1</value>
      <value>0</value>
      <value>0</value>
      <value>0</value>
    </row>
    <row>
      <value>7</value>
      <value>1</value>
      <value>cheng</value>
      <value>3d4f2bf07dc1be38b20cd6e46949a1071f9d0e3d</value>
      <value/>
      <value>陈</value>
      <value>前</value>
      <value>chen@hotmail.com</value>
      <value>69333627</value>
      <value/>
      <value/>
      <value/>
      <value/>
      <value/>
      <value/>
      <value>1</value>
      <value>0</value>
      <value>0</value>
      <value>0</value>
    </row>
    <row>
      <value>8</value>
      <value>2</value>
      <value>linlin</value>
      <value>89235a5c7afee61a8e03161ce64db1edcf0ec8dc</value>
      <value/>
      <value>王</value>
      <value>琳</value>
      <value>wang@hotmail.com</value>
      <value/>
      <value/>
      <value/>
      <value/>
      <value/>
      <value/>
      <value/>
      <value>1</value>
      <value>0</value>
      <value>0</value>
      <value>0</value>
    </row>
    <row>
      <value>9</value>
      <value>1</value>
      <value>seng</value>
      <value>3d4f2bf07dc1be38b20cd6e46949a1071f9d0e3d</value>
      <value/>
      <value>沈</value>
      <value>小勇</value>
      <value>seng@hotmail.com</value>
      <value/>
      <value/>
      <value/>
      <value/>
      <value/>
      <value/>
      <value/>
      <value>1</value>
      <value>0</value>
      <value>0</value>
      <value>0</value>
    </row>
    <row>
      <value>10</value>
      <value>2</value>
      <value>yangjie</value>
      <value>89235a5c7afee61a8e03161ce64db1edcf0ec8dc</value>
      <value/>
      <value>杨</value>
      <value>杰</value>
      <value>yangjie@hotmail.com</value>
      <value/>
      <value/>
      <value/>
      <value/>
      <value/>
      <value/>
      <value/>
      <value>1</value>
      <value>0</value>
      <value>0</value>
      <value>0</value>
    </row>
    <row>
      <value>11</value>
      <value>3</value>
      <value>quan</value>
      <value>3d4f2bf07dc1be38b20cd6e46949a1071f9d0e3d</value>
      <value/>
      <value>全</value>
      <value>心</value>
      <value>quan@hotmail.com</value>
      <value/>
      <value/>
      <value/>
      <value/>
      <value/>
      <value/>
      <value/>
      <value>1</value>
      <value>0</value>
      <value>0</value>
      <value>0</value>
    </row>
    <row>
      <value>12</value>
      <value>1</value>
      <value>lu</value>
      <value>3d4f2bf07dc1be38b20cd6e46949a1071f9d0e3d</value>
      <value/>
      <value>卢</value>
      <value>少鹏</value>
      <value>路lu@hotmail.com</value>
      <value/>
      <value/>
      <value/>
      <value/>
      <value/>
      <value/>
      <value/>
      <value>1</value>
      <value>0</value>
      <value>0</value>
      <value>0</value>
    </row>
    <row>
      <value>13</value>
      <value>1</value>
      <value>jiang</value>
      <value>3d4f2bf07dc1be38b20cd6e46949a1071f9d0e3d</value>
      <value/>
      <value>姜</value>
      <value>峰</value>
      <value>jiang@hotmail.com</value>
      <value/>
      <value/>
      <value/>
      <value/>
      <value/>
      <value/>
      <value/>
      <value>1</value>
      <value>0</value>
      <value>0</value>
      <value>0</value>
    </row>
    <row>
      <value>14</value>
      <value>3</value>
      <value>rong</value>
      <value>3d4f2bf07dc1be38b20cd6e46949a1071f9d0e3d</value>
      <value/>
      <value>刘</value>
      <value>蓉</value>
      <value>rong@hotmail.com</value>
      <value/>
      <value/>
      <value/>
      <value/>
      <value/>
      <value/>
      <value/>
      <value>1</value>
      <value>0</value>
      <value>0</value>
      <value>0</value>
    </row>
    <row>
      <value>15</value>
      <value>2</value>
      <value>ning</value>
      <value>89235a5c7afee61a8e03161ce64db1edcf0ec8dc</value>
      <value/>
      <value>申</value>
      <value>宁宁</value>
      <value>ning@hotmail.com</value>
      <value/>
      <value/>
      <value/>
      <value/>
      <value/>
      <value/>
      <value/>
      <value>1</value>
      <value>0</value>
      <value>0</value>
      <value>0</value>
    </row>
  </table>
	
	
   <table name="tb_sys_role">
    <column>id</column>
    <column>name</column>
    <column>lable</column>
    <column>description</column>
    <row>
      <value>1</value>
      <value>ROLE_ADMIN</value>
      <value>系统管理员</value>
      <value>系统管理员</value>
    </row>
    <row>
      <value>2</value>
      <value>ROLE_USER</value>
      <value>普通用户</value>
      <value>普通用户</value>
    </row>
    <row>
      <value>3</value>
      <value>ROLE_OP</value>
      <value>业务</value>
      <value>业务</value>
    </row>
    <row>
      <value>4</value>
      <value>ROLE_OP_CHARGE</value>
      <value>业务经理</value>
      <value>业务经理</value>
    </row>
    <row>
      <value>5</value>
      <value>ROLE_FINANCE</value>
      <value>财务</value>
      <value>财务</value>
    </row>
    <row>
      <value>6</value>
      <value>ROLE_ARRANGE</value>
      <value>编排</value>
      <value>编排</value>
    </row>
    <row>
      <value>7</value>
      <value>ROLE_DIRECTOR</value>
      <value>主任</value>
      <value>主任</value>
    </row>
    <row>
      <value>8</value>
      <value>ROLE_FI_CHARGE</value>
      <value>财务经理</value>
      <value>财务经理</value>
    </row>
    <row>
      <value>9</value>
      <value>ROLE_INTEG</value>
      <value>综合</value>
      <value>综合</value>
    </row>
    <row>
      <value>10</value>
      <value>ROLE_ING_CHARGE</value>
      <value>综合经理</value>
      <value>综合经理</value>
    </row>
    <row>
      <value>11</value>
      <value>ROLE_MONY</value>
      <value>出纳</value>
      <value>出纳</value>
    </row>
    <row>
      <value>12</value>
      <value>ROLE_CHECK</value>
      <value>审核</value>
      <value>审核</value>
    </row>
    <row>
      <value>13</value>
      <value>ROLE_MIS</value>
      <value>前台</value>
      <value>前台</value>
    </row>	   
  </table>
	
<table name="tb_sys_user_role">
    <column>user_id</column>
    <column>role_id</column>
    <row>
      <value>1</value>
      <value>1</value>
    </row>
    <row>
      <value>2</value>
      <value>2</value>
    </row>
    <row>
      <value>3</value>
      <value>2</value>
    </row>
    <row>
      <value>4</value>
      <value>7</value>
    </row>
    <row>
      <value>5</value>
      <value>4</value>
    </row>
    <row>
      <value>6</value>
      <value>3</value>
    </row>
    <row>
      <value>7</value>
      <value>10</value>
    </row>
    <row>
      <value>9</value>
      <value>6</value>
    </row>
    <row>
      <value>10</value>
      <value>12</value>
    </row>
    <row>
      <value>11</value>
      <value>3</value>
    </row>
  </table>	
	
<table name="tb_sys_resource">
    <column>id</column>
    <column>version</column>
    <column>name</column>
    <column>res_type</column>
    <column>res_string</column>
    <column>memo</column>
    <column>create_by</column>
    <column>create_date</column>
    <column>modify_by</column>
    <column>modify_date</column>
    <row>
      <value>1</value>
      <value>1</value>
      <value>所有连接</value>
      <value>URL</value>
      <value>/../*.html*</value>
      <value/>
      <null/>
      <null/>
      <null/>
      <null/>
    </row>
    <row>
      <value>2</value>
      <value>0</value>
      <value>用户（浏览）</value>
      <value>URL</value>
      <value>/users.html*</value>
      <value/>
      <null/>
      <null/>
      <null/>
      <null/>
    </row>
    <row>
      <value>3</value>
      <value>0</value>
      <value>用户（修改）</value>
      <value>METHOD</value>
      <value>com.vriche.adrm.service.UserManager.saveUser</value>
      <value/>
      <null/>
      <null/>
      <null/>
      <null/>
    </row>
    <row>
      <value>4</value>
      <value>0</value>
      <value>合同（浏览）</value>
      <value>URL</value>
      <value>/contracts.html*</value>
      <value/>
      <null/>
      <null/>
      <null/>
      <null/>
    </row>
    <row>
      <value>5</value>
      <value>0</value>
      <value>组织信息(浏览)</value>
      <value>URL</value>
      <value>/orgs.html*</value>
      <value/>
      <null/>
      <null/>
      <null/>
      <null/>
    </row>
    <row>
      <value>6</value>
      <value>0</value>
      <value>部门(浏览)</value>
      <value>URL</value>
      <value>/branchs.html*</value>
      <value/>
      <null/>
      <null/>
      <null/>
      <null/>
    </row>
    <row>
      <value>7</value>
      <value>0</value>
      <value>流程管理(浏览)</value>
      <value>URL</value>
      <value>/oaworkflows.html*</value>
      <value/>
      <null/>
      <null/>
      <null/>
      <null/>
    </row>
    <row>
      <value>8</value>
      <value>0</value>
      <value>流程管理(修改)</value>
      <value>METHOD</value>
      <value>com.vriche.adrm.service.OaWorkFlowManager.saveOaWorkFlow</value>
      <value/>
      <null/>
      <null/>
      <null/>
      <null/>
    </row>
    <row>
      <value>9</value>
      <value>0</value>
      <value>权限控制(浏览)</value>
      <value>URL</value>
      <value>/syspermitmanager.html*</value>
      <value/>
      <null/>
      <null/>
      <null/>
      <null/>
    </row>
    <row>
      <value>10</value>
      <value>0</value>
      <value>办公审批</value>
      <value>URL</value>
      <value>/oaworkflowchecks.html*</value>
      <value/>
      <null/>
      <null/>
      <null/>
      <null/>
    </row>
    <row>
      <value>11</value>
      <value>0</value>
      <value>职位设置(浏览)</value>
      <value>URL</value>
      <value>/roles.html*</value>
      <value/>
      <null/>
      <null/>
      <null/>
      <null/>
    </row>
    <row>
      <value>12</value>
      <value>0</value>
      <value>行业代理信息</value>
      <value>TAG</value>
      <value>table.industryagent</value>
      <value/>
      <null/>
      <null/>
      <null/>
      <null/>
    </row>
    <row>
      <value>13</value>
      <value>0</value>
      <value>桌面</value>
      <value>URL</value>
      <value>/mainmenu.html*</value>
      <value/>
      <null/>
      <null/>
      <null/>
      <null/>
    </row>
  </table>
  
	
   <table name="tb_sys_org">
    <column>sys_org_id</column>
    <column>version</column>
    <column>name</column>
    <column>bank_code</column>
    <column>bank_name</column>
    <column>fax</column>
    <column>link_man</column>
    <column>tel</column>
    <column>create_by</column>
    <column>create_date</column>
    <column>modify_by</column>
    <column>modify_date</column>
    <column>address</column>
    <column>city</column>
    <column>province</column>
    <column>country</column>
    <column>postal_code</column>
    <row>
      <value>1</value>
      <value>0</value>
      <value>河南有线广告经营部</value>
      <value>广告经营部</value>
      <value/>
      <value>69333625</value>
      <value>曾嵘</value>
      <value/>
      <null/>
      <null/>
      <null/>
      <null/>
      <value/>
      <value>中国</value>
      <value>河南省</value>
      <value>北京</value>
      <value>100876</value>
    </row>
  </table>
	
  <table name="tb_sys_branch">
    <column>sys_branch_id</column>
    <column>version</column>
    <column>name</column>
    <column>sys_org_id</column>
    <column>parent_id</column>
    <column>tree_level</column>
    <column>display_no</column>
    <column>create_by</column>
    <column>create_date</column>
    <column>modify_by</column>
    <column>modify_date</column>
    <row>
      <value>3</value>
      <value>0</value>
      <value>主任办公室</value>
      <value>1</value>
      <value>0</value>
      <null/>
      <value>1</value>
      <null/>
      <null/>
      <null/>
      <null/>
    </row>
    <row>
      <value>4</value>
      <value>0</value>
      <value>业务一部</value>
      <value>1</value>
      <value>0</value>
      <null/>
      <value>2</value>
      <null/>
      <null/>
      <null/>
      <null/>
    </row>
    <row>
      <value>5</value>
      <value>0</value>
      <value>业务二部</value>
      <value>1</value>
      <value>0</value>
      <null/>
      <value>3</value>
      <null/>
      <null/>
      <null/>
      <null/>
    </row>
    <row>
      <value>6</value>
      <value>0</value>
      <value>统协部门</value>
      <value>1</value>
      <value>0</value>
      <null/>
      <value>4</value>
      <null/>
      <null/>
      <null/>
      <null/>
    </row>
    <row>
      <value>7</value>
      <value>0</value>
      <value>帐管部</value>
      <value>1</value>
      <value>0</value>
      <null/>
      <value>5</value>
      <null/>
      <null/>
      <null/>
      <null/>
    </row>
    <row>
      <value>8</value>
      <value>0</value>
      <value>编播部</value>
      <value>1</value>
      <value>0</value>
      <null/>
      <value>6</value>
      <null/>
      <null/>
      <null/>
      <null/>
    </row>
    <row>
      <value>19</value>
      <value>0</value>
      <value>审核部</value>
      <value>1</value>
      <value>0</value>
      <null/>
      <value>7</value>
      <null/>
      <null/>
      <null/>
      <null/>
    </row>
  </table>
<!--SysUserType-START-->	
  <table name="tb_sys_user_type">
    <column>sys_user_type_id</column>
    <column>version</column>
    <column>name</column>
    <column>value</column>
    <column>create_by</column>
    <column>create_date</column>
    <column>modify_by</column>
    <column>modify_date</column>
    <row>
      <value>1</value>
      <value>0</value>
      <value>全部</value>
      <value>1</value>
      <null/>
      <null/>
      <null/>
      <null/>
    </row>
    <row>
      <value>2</value>
      <value>0</value>
      <value>部门</value>
      <value>2</value>
      <null/>
      <null/>
      <null/>
      <null/>
    </row>
    <row>
      <value>3</value>
      <value>0</value>
      <value>职位</value>
      <value>3</value>
      <null/>
      <null/>
      <null/>
      <null/>
    </row>
    <row>
      <value>4</value>
      <value>0</value>
      <value>个人</value>
      <value>4</value>
      <null/>
      <null/>
      <null/>
      <null/>
    </row>
  </table>
  <!--SysUserType-END-->		
	
	
	
	
	
	
  
 <table name="tb_customer_category">
    <column>customer_category_id</column>
    <column>version</column>
    <column>ad_resource_price_type</column>
    <column>category_code</column>
    <column>category_name</column>
    <column>display_no</column>
    <column>memo</column>
    <column>parent_id</column>
    <column>tree_level</column>
    <column>create_by</column>
    <column>create_date</column>
    <column>modify_by</column>
    <column>modify_date</column>
    <row>
      <value>1</value>
      <value>0</value>
      <null/>
      <value/>
      <value>代理客户</value>
      <value>0</value>
      <null/>
      <null/>
      <value>0</value>
      <null/>
      <null/>
      <null/>
      <null/>
    </row>
    <row>
      <value>2</value>
      <value>0</value>
      <null/>
      <value/>
      <value>直接客户</value>
      <value>1</value>
      <null/>
      <null/>
      <value>0</value>
      <null/>
      <null/>
      <null/>
      <null/>
    </row>
    <row>
      <value>3</value>
      <value>0</value>
      <null/>
      <value/>
      <value>其它客户</value>
      <value>2</value>
      <null/>
      <null/>
      <value>0</value>
      <null/>
      <null/>
      <null/>
      <null/>
    </row>
  </table>
	
<table name="tb_customer_type">
    <column>customer_type_id</column>
    <column>version</column>
    <column>create_by</column>
    <column>create_date</column>
    <column>modify_by</column>
    <column>modify_date</column>
    <column>code</column>
    <column>memo</column>
    <column>name</column>
    <row>
      <value>1</value>
      <value>0</value>
      <null/>
      <null/>
      <null/>
      <null/>
      <null/>
      <null/>
      <value>国有</value>
    </row>
    <row>
      <value>2</value>
      <value>0</value>
      <null/>
      <null/>
      <null/>
      <null/>
      <null/>
      <null/>
      <value>外企</value>
    </row>
    <row>
      <value>3</value>
      <value>0</value>
      <null/>
      <null/>
      <null/>
      <null/>
      <null/>
      <null/>
      <value>合资</value>
    </row>
    <row>
      <value>4</value>
      <value>0</value>
      <null/>
      <null/>
      <null/>
      <null/>
      <null/>
      <null/>
      <value>私营</value>
    </row>
  </table>
		
  <table name="tb_customer_industry_type">
    <column>customer_industry_type_id</column>
    <column>version</column>
    <column>create_by</column>
    <column>create_date</column>
    <column>modify_by</column>
    <column>modify_date</column>
    <column>memo</column>
    <column>name</column>
    <column>code</column>
    <row>
      <value>1</value>
      <value>1</value>
      <null/>
      <null/>
      <null/>
      <null/>
      <value/>
      <value>汽车品牌</value>
      <value>001</value>
    </row>
    <row>
      <value>2</value>
      <value>1</value>
      <null/>
      <null/>
      <null/>
      <null/>
      <value/>
      <value>交通汽车配件市场</value>
      <value>002</value>
    </row>
    <row>
      <value>3</value>
      <value>1</value>
      <null/>
      <null/>
      <null/>
      <null/>
      <value/>
      <value>房地产行业</value>
      <value>003</value>
    </row>
    <row>
      <value>4</value>
      <value>0</value>
      <null/>
      <null/>
      <null/>
      <null/>
      <value/>
      <value>药品保健品</value>
      <value>004</value>
    </row>
    <row>
      <value>5</value>
      <value>0</value>
      <null/>
      <null/>
      <null/>
      <null/>
      <value/>
      <value>医疗行业</value>
      <value>005</value>
    </row>
    <row>
      <value>6</value>
      <value>0</value>
      <null/>
      <null/>
      <null/>
      <null/>
      <value/>
      <value>烟酒行业</value>
      <value>006</value>
    </row>
    <row>
      <value>7</value>
      <value>0</value>
      <null/>
      <null/>
      <null/>
      <null/>
      <value/>
      <value>日用品化妆品</value>
      <value>007</value>
    </row>
    <row>
      <value>8</value>
      <value>0</value>
      <null/>
      <null/>
      <null/>
      <null/>
      <value/>
      <value>餐饮娱乐行业</value>
      <value>008</value>
    </row>
    <row>
      <value>9</value>
      <value>0</value>
      <null/>
      <null/>
      <null/>
      <null/>
      <value/>
      <value>金融、保险、邮政行业</value>
      <value>009</value>
    </row>
    <row>
      <value>10</value>
      <value>0</value>
      <null/>
      <null/>
      <null/>
      <null/>
      <value/>
      <value>通讯行业</value>
      <value>010</value>
    </row>
    <row>
      <value>11</value>
      <value>0</value>
      <null/>
      <null/>
      <null/>
      <null/>
      <value/>
      <value>装饰公司家装市场行业</value>
      <value>011</value>
    </row>
    <row>
      <value>12</value>
      <value>0</value>
      <null/>
      <null/>
      <null/>
      <null/>
      <value/>
      <value>家居建材品牌</value>
      <value>012</value>
    </row>
    <row>
      <value>13</value>
      <value>0</value>
      <null/>
      <null/>
      <null/>
      <null/>
      <value/>
      <value>商城市场（卖场）超市</value>
      <value>013</value>
    </row>
    <row>
      <value>14</value>
      <value>0</value>
      <null/>
      <null/>
      <null/>
      <null/>
      <value/>
      <value>服装饰品行业</value>
      <value>014</value>
    </row>
    <row>
      <value>15</value>
      <value>0</value>
      <null/>
      <null/>
      <null/>
      <null/>
      <value/>
      <value>婚庆、摄影</value>
      <value>015</value>
    </row>
    <row>
      <value>16</value>
      <value>0</value>
      <null/>
      <null/>
      <null/>
      <null/>
      <value/>
      <value>文化教育体育</value>
      <value>016</value>
    </row>
    <row>
      <value>17</value>
      <value>0</value>
      <null/>
      <null/>
      <null/>
      <null/>
      <value/>
      <value>旅游行业</value>
      <value>017</value>
    </row>
    <row>
      <value>18</value>
      <value>0</value>
      <null/>
      <null/>
      <null/>
      <null/>
      <value/>
      <value>家电、IT短信行业</value>
      <value>018</value>
    </row>
    <row>
      <value>19</value>
      <value>0</value>
      <null/>
      <null/>
      <null/>
      <null/>
      <value/>
      <value>食品、饮料</value>
      <value>019</value>
    </row>
    <row>
      <value>20</value>
      <value>0</value>
      <null/>
      <null/>
      <null/>
      <null/>
      <value/>
      <value>综合类</value>
      <value>020</value>
    </row>
  </table>



 <table name="tb_ad_resource_type">
    <column>ad_ad_resource_type_id</column>
    <column>version</column>
    <column>name</column>
    <column>value</column>
    <column>create_by</column>
    <column>create_date</column>
    <column>modify_by</column>
    <column>modify_date</column>
    <column>enable</column>
    <column>memo</column>
    <row>
      <value>1</value>
      <value>0</value>
      <value>普通</value>
      <value>1</value>
      <null/>
      <null/>
      <null/>
      <null/>
      <value>1</value>
      <null/>
    </row>
    <row>
      <value>2</value>
      <value>0</value>
      <value>黄金</value>
      <value>1</value>
      <null/>
      <null/>
      <null/>
      <null/>
      <value>1</value>
      <null/>
    </row>
    <row>
      <value>3</value>
      <value>0</value>
      <value>特殊</value>
      <value>1</value>
      <null/>
      <null/>
      <null/>
      <null/>
      <value>1</value>
      <null/>
    </row>
  </table>	
	
<table name="tb_ad_resource_mediaorg">
    <column>ad_resource_mediaorg_id</column>
    <column>version</column>
    <column>name</column>
    <column>value</column>
    <column>create_by</column>
    <column>create_date</column>
    <column>modify_by</column>
    <column>modify_date</column>
    <column>enable</column>
    <column>memo</column>
    <row>
      <value>1</value>
      <value>0</value>
      <value>中央电视台</value>
      <null/>
      <null/>
      <null/>
      <null/>
      <null/>
      <value>1</value>
      <null/>
    </row>
    <row>
      <value>2</value>
      <value>0</value>
      <value>北京电视台</value>
      <null/>
      <null/>
      <null/>
      <null/>
      <null/>
      <value>1</value>
      <null/>
    </row>
    <row>
      <value>3</value>
      <value>0</value>
      <value>上海电视台</value>
      <null/>
      <null/>
      <null/>
      <null/>
      <null/>
      <value>1</value>
      <null/>
    </row>
  </table>
		
 <table name="tb_ad_resource_channel">
    <column>resource_mediaorg_id</column>
    <column>version</column>
    <column>name</column>
    <column>value</column>
    <column>create_by</column>
    <column>create_date</column>
    <column>modify_by</column>
    <column>modify_date</column>
    <column>enable</column>
    <column>memo</column>
    <row>
      <value>1</value>
      <value>0</value>
      <value>一套</value>
      <null/>
      <null/>
      <null/>
      <null/>
      <null/>
      <value>1</value>
      <null/>
    </row>
    <row>
      <value>2</value>
      <value>0</value>
      <value>二套</value>
      <null/>
      <null/>
      <null/>
      <null/>
      <null/>
      <value>1</value>
      <null/>
    </row>
    <row>
      <value>3</value>
      <value>0</value>
      <value>三套</value>
      <null/>
      <null/>
      <null/>
      <null/>
      <null/>
      <value>1</value>
      <null/>
    </row>
    <row>
      <value>4</value>
      <value>0</value>
      <value>四套</value>
      <null/>
      <null/>
      <null/>
      <null/>
      <null/>
      <value>1</value>
      <null/>
    </row>
    <row>
      <value>5</value>
      <value>0</value>
      <value>五套</value>
      <null/>
      <null/>
      <null/>
      <null/>
      <null/>
      <value>1</value>
      <null/>
    </row>
    <row>
      <value>6</value>
      <value>0</value>
      <value>六套</value>
      <null/>
      <null/>
      <null/>
      <null/>
      <null/>
      <value>1</value>
      <null/>
    </row>
    <row>
      <value>7</value>
      <value>0</value>
      <value>七套</value>
      <null/>
      <null/>
      <null/>
      <null/>
      <null/>
      <value>1</value>
      <null/>
    </row>
    <row>
      <value>8</value>
      <value>0</value>
      <value>八套</value>
      <null/>
      <null/>
      <null/>
      <null/>
      <null/>
      <value>1</value>
      <null/>
    </row>
    <row>
      <value>9</value>
      <value>0</value>
      <value>九套</value>
      <null/>
      <null/>
      <null/>
      <null/>
      <null/>
      <value>1</value>
      <null/>
    </row>
    <row>
      <value>10</value>
      <value>0</value>
      <value>十套</value>
      <null/>
      <null/>
      <null/>
      <null/>
      <null/>
      <value>1</value>
      <null/>
    </row>
    <row>
      <value>11</value>
      <value>0</value>
      <value>十一套</value>
      <null/>
      <null/>
      <null/>
      <null/>
      <null/>
      <value>1</value>
      <null/>
    </row>
    <row>
      <value>12</value>
      <value>0</value>
      <value>十二套</value>
      <null/>
      <null/>
      <null/>
      <null/>
      <null/>
      <value>1</value>
      <null/>
    </row>
    <row>
      <value>13</value>
      <value>0</value>
      <value>十三套</value>
      <null/>
      <null/>
      <null/>
      <null/>
      <null/>
      <value>1</value>
      <null/>
    </row>
  </table>	
			
   <table name="tb_ad_resource_carrier_type">
    <column>ad_resource_carrier_type_id</column>
    <column>version</column>
    <column>create_by</column>
    <column>create_date</column>
    <column>modify_by</column>
    <column>modify_date</column>
    <column>enable</column>
    <column>name</column>
    <column>parent_id</column>
    <column>node_level</column>
    <column>display_no</column>
    <column>nodePath</column>
    <column>memo</column>
    <row>
      <value>1</value>
      <value>0</value>
      <null/>
      <null/>
      <null/>
      <null/>
      <value>1</value>
      <value>电视</value>
      <value>0</value>
      <value>0</value>
      <value>1</value>
      <null/>
      <null/>
    </row>
    <row>
      <value>2</value>
      <value>0</value>
      <null/>
      <null/>
      <null/>
      <null/>
      <value>1</value>
      <value>报纸</value>
      <value>0</value>
      <value>0</value>
      <value>2</value>
      <null/>
      <null/>
    </row>
    <row>
      <value>3</value>
      <value>0</value>
      <null/>
      <null/>
      <null/>
      <null/>
      <value>1</value>
      <value>杂志</value>
      <value>0</value>
      <value>0</value>
      <value>3</value>
      <null/>
      <null/>
    </row>
    <row>
      <value>4</value>
      <value>0</value>
      <null/>
      <null/>
      <null/>
      <null/>
      <value>1</value>
      <value>互连网</value>
      <value>0</value>
      <value>0</value>
      <value>4</value>
      <null/>
      <null/>
    </row>
  </table>
		
 
	
	
 
	
	
 <table name="tb_ad_resource_specific">
    <column>ad_resource_specific_id</column>
    <column>version</column>
    <column>create_by</column>
    <column>create_date</column>
    <column>modify_by</column>
    <column>modify_date</column>
    <column>memo</column>
    <column>position</column>
    <column>name</column>
    <column>over_rate</column>
    <row>
      <value>1</value>
      <value>0</value>
      <null/>
      <null/>
      <null/>
      <null/>
      <null/>
      <value>1</value>
      <value>正一</value>
      <value>0.2</value>
    </row>
    <row>
      <value>2</value>
      <value>0</value>
      <value>1</value>
      <value><![CDATA[2006-10-17 00:00:00.0]]></value>
      <value>1</value>
      <value><![CDATA[2006-10-17 00:00:00.0]]></value>
      <value>1</value>
      <value>2</value>
      <value>正二</value>
      <value>0.2</value>
    </row>
    <row>
      <value>3</value>
      <value>0</value>
      <value>1</value>
      <value><![CDATA[2006-10-17 00:00:00.0]]></value>
      <value>1</value>
      <value><![CDATA[2006-10-17 00:00:00.0]]></value>
      <value>1</value>
      <value>3</value>
      <value>正三</value>
      <value>0.2</value>
    </row>
    <row>
      <value>4</value>
      <value>0</value>
      <null/>
      <null/>
      <null/>
      <null/>
      <null/>
      <value>4</value>
      <value>正四</value>
      <value>0.2</value>
    </row>
    <row>
      <value>5</value>
      <value>0</value>
      <null/>
      <null/>
      <null/>
      <null/>
      <null/>
      <value>5</value>
      <value>正五</value>
      <value>0.2</value>
    </row>
    <row>
      <value>6</value>
      <value>0</value>
      <null/>
      <null/>
      <null/>
      <null/>
      <null/>
      <value>6</value>
      <value>正六</value>
      <value>0.2</value>
    </row>
		  
    <row>
      <value>7</value>
      <value>0</value>
      <null/>
      <null/>
      <null/>
      <null/>
      <null/>
      <value>7</value>
      <value>正七</value>
      <value>0.2</value>
    </row>
    <row>
      <value>8</value>
      <value>0</value>
      <null/>
      <null/>
      <null/>
      <null/>
      <null/>
      <value>8</value>
      <value>正八</value>
      <value>0.2</value>
    </row>
    <row>
      <value>9</value>
      <value>0</value>
      <null/>
      <null/>
      <null/>
      <null/>
      <null/>
      <value>9</value>
      <value>正九</value>
      <value>0.2</value>
    </row>
    <row>
      <value>10</value>
      <value>0</value>
      <null/>
      <null/>
      <null/>
      <null/>
      <null/>
      <value>A</value>
      <value>倒一</value>
      <value>0.2</value>
    </row>
    <row>
      <value>11</value>
      <value>0</value>
      <null/>
      <null/>
      <null/>
      <null/>
      <null/>
      <value>B</value>
      <value>倒二</value>
      <value>0.2</value>
    </row>
    <row>
      <value>12</value>
      <value>0</value>
      <null/>
      <null/>
      <null/>
      <null/>
      <null/>
      <value>C</value>
      <value>倒三</value>
      <value>0.2</value>
    </row>
    <row>
      <value>13</value>
      <value>0</value>
      <null/>
      <null/>
      <null/>
      <null/>
      <null/>
      <value>D</value>
      <value>倒四</value>
      <value>0.2</value>
    </row>
    <row>
      <value>14</value>
      <value>0</value>
      <null/>
      <null/>
      <null/>
      <null/>
      <null/>
      <value>E</value>
      <value>倒五</value>
      <value>0.2</value>
    </row>
    <row>
      <value>15</value>
      <value>0</value>
      <null/>
      <null/>
      <null/>
      <null/>
      <null/>
      <value>F</value>
      <value>倒六</value>
      <value>0.2</value>
    </row>
    <row>
      <value>16</value>
      <value>0</value>
      <null/>
      <null/>
      <null/>
      <null/>
      <null/>
      <value>G</value>
      <value>倒七</value>
      <value>0.2</value>
    </row>
    <row>
      <value>17</value>
      <value>0</value>
      <null/>
      <null/>
      <null/>
      <null/>
      <null/>
      <value>H</value>
      <value>倒八</value>
      <value>0.2</value>
    </row>
    <row>
      <value>18</value>
      <value>0</value>
      <null/>
      <null/>
      <null/>
      <null/>
      <null/>
      <value>I</value>
      <value>倒九</value>
      <value>0.2</value>
    </row>
  </table>
	



	
	
	
	

  <table name="tb_ad_resource_price_type">
    <column>ad_resource_price_type_id</column>
    <column>version</column>
    <column>price_type_name</column>
    <column>value</column>
    <column>create_by</column>
    <column>create_date</column>
    <column>modify_by</column>
    <column>modify_date</column>
    <column>enable</column>
    <column>memo</column>
    <row>
      <value>1</value>
      <value>0</value>
      <value>刊例价格</value>
      <value>4</value>
      <null/>
      <null/>
      <null/>
      <null/>
      <value>1</value>
      <null/>
    </row>
    <row>
      <value>2</value>
      <value>0</value>
      <value>周价格</value>
      <value>1</value>
      <null/>
      <null/>
      <null/>
      <null/>
      <value>1</value>
      <null/>
    </row>
    <row>
      <value>3</value>
      <value>0</value>
      <value>月价格</value>
      <value>2</value>
      <null/>
      <null/>
      <null/>
      <null/>
      <value>1</value>
      <null/>
    </row>
    <row>
      <value>4</value>
      <value>0</value>
      <value>季价格</value>
      <value>3</value>
      <null/>
      <null/>
      <null/>
      <null/>
      <value>1</value>
      <null/>
    </row>
    <row>
      <value>5</value>
      <value>0</value>
      <value>年价格</value>
      <value>5</value>
      <null/>
      <null/>
      <null/>
      <null/>
      <value>1</value>
      <null/>
    </row>
    <row>
      <value>6</value>
      <value>0</value>
      <value>半年价</value>
      <value>6</value>
      <null/>
      <null/>
      <null/>
      <null/>
      <value>1</value>
      <null/>
    </row> 
  </table>
  
 
  
	
	
	
	
	
	
  
  <!--OrderCategory-START-->
    <table name="tb_order_category">
    <column>order_category_id</column>
    <column>version</column>
    <column>name</column>
    <column>parent_id</column>
    <column>node_level</column>
    <column>node_path</column>
    <column>create_by</column>
    <column>create_date</column>
    <column>modify_by</column>
    <column>modify_date</column>
    <column>value</column>
    <column>calculate_auto</column>
    <column>displayNo</column>
    <row>
      <value>1</value>
      <value>0</value>
      <value>正常</value>
      <value>0</value>
      <value>0</value>
      <value>1</value>
      <null/>
      <null/>
      <null/>
      <null/>
      <value>A</value>
      <value>1</value>
      <value>1</value>
    </row>
    <row>
      <value>2</value>
      <value>0</value>
      <value>协议</value>
      <value>0</value>
      <value>0</value>
      <value>1</value>
      <null/>
      <null/>
      <null/>
      <null/>
      <value>B</value>
      <value>1</value>
      <value>0</value>
    </row>
    <row>
      <value>3</value>
      <value>1</value>
      <value>协约</value>
      <value>0</value>
      <value>0</value>
      <value>1</value>
      <value>1</value>
      <value><![CDATA[2006-10-17 00:00:00.0]]></value>
      <value>1</value>
      <value><![CDATA[2006-10-17 00:00:00.0]]></value>
      <value>C</value>
      <value>0</value>
      <value>3</value>
    </row>
    <row>
      <value>4</value>
      <value>0</value>
      <value>正常</value>
      <value>1</value>
      <value>2</value>
      <value/>
      <null/>
      <null/>
      <null/>
      <null/>
      <value/>
      <value>1</value>
      <value>0</value>
    </row>
    <row>
      <value>5</value>
      <value>0</value>
      <value>赠播</value>
      <value>1</value>
      <value>2</value>
      <value/>
      <null/>
      <null/>
      <null/>
      <null/>
      <value/>
      <value>0</value>
      <value>0</value>
    </row>
    <row>
      <value>6</value>
      <value>0</value>
      <value>补播</value>
      <value>1</value>
      <value>2</value>
      <value/>
      <null/>
      <null/>
      <null/>
      <null/>
      <value/>
      <value>0</value>
      <value>0</value>
    </row>
    <row>
      <value>7</value>
      <value>0</value>
      <value>抵偿</value>
      <value>1</value>
      <value>2</value>
      <value/>
      <null/>
      <null/>
      <null/>
      <null/>
      <value/>
      <value>0</value>
      <value>0</value>
    </row>
    <row>
      <value>8</value>
      <value>0</value>
      <value>抵顶</value>
      <value>2</value>
      <value>2</value>
      <value/>
      <null/>
      <null/>
      <null/>
      <null/>
      <value/>
      <value>0</value>
      <value>0</value>
    </row>
    <row>
      <value>9</value>
      <value>0</value>
      <value>正常</value>
      <value>2</value>
      <value>0</value>
      <value/>
      <null/>
      <null/>
      <null/>
      <null/>
      <value/>
      <value>1</value>
      <value>0</value>
    </row>
    <row>
      <value>10</value>
      <value>0</value>
      <value>赠播</value>
      <value>2</value>
      <value>0</value>
      <value/>
      <null/>
      <null/>
      <null/>
      <null/>
      <value/>
      <value>0</value>
      <value>0</value>
    </row>
    <row>
      <value>11</value>
      <value>0</value>
      <value>补播</value>
      <value>2</value>
      <value>0</value>
      <value/>
      <null/>
      <null/>
      <null/>
      <null/>
      <value/>
      <value>0</value>
      <value>0</value>
    </row>
    <row>
      <value>12</value>
      <value>0</value>
      <value>补偿</value>
      <value>2</value>
      <value>0</value>
      <value/>
      <null/>
      <null/>
      <null/>
      <null/>
      <value/>
      <value>0</value>
      <value>0</value>
    </row>
    <row>
      <value>13</value>
      <value>0</value>
      <value>正常</value>
      <value>3</value>
      <value>0</value>
      <value/>
      <null/>
      <null/>
      <null/>
      <null/>
      <value/>
      <value>1</value>
      <value>0</value>
    </row>
    <row>
      <value>14</value>
      <value>0</value>
      <value>赠播</value>
      <value>3</value>
      <value>0</value>
      <value/>
      <null/>
      <null/>
      <null/>
      <null/>
      <value/>
      <value>0</value>
      <value>0</value>
    </row>
    <row>
      <value>15</value>
      <value>0</value>
      <value>补播</value>
      <value>3</value>
      <value>0</value>
      <value/>
      <null/>
      <null/>
      <null/>
      <null/>
      <value/>
      <value>0</value>
      <value>0</value>
    </row>
    <row>
      <value>16</value>
      <value>0</value>
      <value>补偿</value>
      <value>3</value>
      <value>0</value>
      <value/>
      <null/>
      <null/>
      <null/>
      <null/>
      <value/>
      <value>0</value>
      <value>0</value>
    </row>
    <row>
      <value>17</value>
      <value>0</value>
      <value>抵顶</value>
      <value>3</value>
      <value>0</value>
      <value/>
      <null/>
      <null/>
      <null/>
      <null/>
      <value/>
      <value>0</value>
      <value>0</value>
    </row>
  </table>
  <!--OrderCategory-END-->
  
<table name="tb_income_mode">
    <column>income_mode_id</column>
    <column>version</column>
    <column>create_by</column>
    <column>create_date</column>
    <column>modify_by</column>
    <column>modify_date</column>
    <column>name</column>
    <column>value</column>
    <row>
      <value>1</value>
      <value>0</value>
      <null/>
      <null/>
      <null/>
      <null/>
      <value>支票</value>
      <value>1</value>
    </row>
    <row>
      <value>2</value>
      <value>0</value>
      <null/>
      <null/>
      <null/>
      <null/>
      <value>承兑</value>
      <value>2</value>
    </row>
    <row>
      <value>3</value>
      <value>0</value>
      <null/>
      <null/>
      <null/>
      <null/>
      <value>电汇</value>
      <value>3</value>
    </row>
    <row>
      <value>4</value>
      <value>0</value>
      <null/>
      <null/>
      <null/>
      <null/>
      <value>现金</value>
      <value>4</value>
    </row>
    <row>
      <value>5</value>
      <value>0</value>
      <null/>
      <null/>
      <null/>
      <null/>
      <value>转帐</value>
      <value>5</value>
    </row>
    <row>
      <value>6</value>
      <value>0</value>
      <null/>
      <null/>
      <null/>
      <null/>
      <value>其他</value>
      <value>6</value>
    </row>
  </table>
	
<table name="tb_income_purpose">
    <column>income_purpose_id</column>
    <column>version</column>
    <column>create_by</column>
    <column>create_date</column>
    <column>modify_by</column>
    <column>modify_date</column>
    <column>name</column>
    <column>value</column>
    <row>
      <value>1</value>
      <value>0</value>
      <null/>
      <null/>
      <null/>
      <null/>
      <value>广告费</value>
      <value>1</value>
    </row>
    <row>
      <value>2</value>
      <value>0</value>
      <null/>
      <null/>
      <null/>
      <null/>
      <value>抵顶</value>
      <value>2</value>
    </row>
    <row>
      <value>3</value>
      <value>0</value>
      <null/>
      <null/>
      <null/>
      <null/>
      <value>返点</value>
      <value>3</value>
    </row>
    <row>
      <value>4</value>
      <value>0</value>
      <null/>
      <null/>
      <null/>
      <null/>
      <value>广告费</value>
      <value>4</value>
    </row>
    <row>
      <value>5</value>
      <value>0</value>
      <null/>
      <null/>
      <null/>
      <null/>
      <value>合作合拍</value>
      <value>5</value>
    </row>
    <row>
      <value>6</value>
      <value>0</value>
      <null/>
      <null/>
      <null/>
      <null/>
      <value>往年到款</value>
      <value>6</value>
    </row>
    <row>
      <value>7</value>
      <value>0</value>
      <null/>
      <null/>
      <null/>
      <null/>
      <value>往年欠款</value>
      <value>7</value>
    </row>
    <row>
      <value>8</value>
      <value>0</value>
      <null/>
      <null/>
      <null/>
      <null/>
      <value>预付款</value>
      <value>8</value>
    </row>
    <row>
      <value>9</value>
      <value>0</value>
      <null/>
      <null/>
      <null/>
      <null/>
      <value>制作费</value>
      <value>9</value>
    </row>
    <row>
      <value>10</value>
      <value>0</value>
      <null/>
      <null/>
      <null/>
      <null/>
      <value>保证金</value>
      <value>10</value>
    </row>	
  </table>	
		
	
  <!--OaAreaCity-START-->
	
  <!--OaAreaCity-END-->
	
	
	
  <!--OaAreaPc-START-->

  <!--OaAreaPc-END-->
	
	
	
	
	
  <!--OaAssetsState-START-->
 <table name="tb_oa_assets_state">
    <column>assets_state_id</column>
    <column>version</column>
    <column>name</column>
    <column>value</column>
    <column>create_by</column>
    <column>create_date</column>
    <column>modify_by</column>
    <column>modify_date</column>
    <row>
      <value>1</value>
      <value>0</value>
      <value>正常</value>
      <null/>
      <null/>
      <null/>
      <null/>
      <null/>
    </row>
    <row>
      <value>2</value>
      <value>0</value>
      <value>报废</value>
      <null/>
      <null/>
      <null/>
      <null/>
      <null/>
    </row>
  </table>
  <!--OaAssetsState-END-->
	
	
  <!--OaAssetsType-START-->
 <table name="tb_oa_assets_type">
    <column>assets_type_id</column>
    <column>version</column>
    <column>name</column>
    <column>value</column>
    <column>create_by</column>
    <column>create_date</column>
    <column>modify_by</column>
    <column>modify_date</column>
    <row>
      <value>1</value>
      <value>0</value>
      <value>外购资产</value>
      <null/>
      <null/>
      <null/>
      <null/>
      <null/>
    </row>
    <row>
      <value>2</value>
      <value>0</value>
      <value>自建资产</value>
      <null/>
      <null/>
      <null/>
      <null/>
      <null/>
    </row>
  </table>
  <!--OaAssetsType-END-->
	
	
  <!--OaBusinessCardType-START-->
 <table name="tb_oa_business_card_type">
    <column>business_card_typ_id</column>
    <column>version</column>
    <column>name</column>
    <column>value</column>
    <column>create_by</column>
    <column>create_date</column>
    <column>modify_by</column>
    <column>modify_date</column>
    <row>
      <value>1</value>
      <value>0</value>
      <value>朋友</value>
      <null/>
      <null/>
      <null/>
      <null/>
      <null/>
    </row>
    <row>
      <value>2</value>
      <value>0</value>
      <value>家人</value>
      <null/>
      <null/>
      <null/>
      <null/>
      <null/>
    </row>
  </table>
  <!--OaBusinessCardType-END-->
	

  <!--OaDocumentCatalog-START-->

  <!--OaDocumentCatalog-END-->
	
	
	
  <!--OaDocumentCatalogPermitType-START-->
  <table name="tb_oa_document_catalog_permit_type">
    <column>value</column>
    <column>permit_type_id</column>
    <column>version</column>
    <column>name</column>
    <column>create_by</column>
    <column>create_date</column>
    <column>modify_by</column>
    <column>modify_date</column>
    <row>
      <value>2</value>
      <value>1</value>
      <value>0</value>
      <value>发布</value>
      <null/>
      <null/>
      <null/>
      <null/>
    </row>
    <row>
      <value>1</value>
      <value>2</value>
      <value>0</value>
      <value>浏</value>
      <null/>
      <null/>
      <null/>
      <null/>
    </row>
  </table>
  <!--OaDocumentCatalogPermitType-END-->
	
	
  <!--OaInfoType-START-->
 <table name="tb_oa_info_type">
    <column>info_type_id</column>
    <column>version</column>
    <column>name</column>
    <column>value</column>
    <column>create_by</column>
    <column>create_date</column>
    <column>modify_by</column>
    <column>modify_date</column>
    <row>
      <value>1</value>
      <value>0</value>
      <value>通知</value>
      <null/>
      <null/>
      <null/>
      <null/>
      <null/>
    </row>
    <row>
      <value>2</value>
      <value>0</value>
      <value>新闻</value>
      <null/>
      <null/>
      <null/>
      <null/>
      <null/>
    </row>
  </table>
  <!--OaInfoType-END-->
	
	
	
  <!--OaProductType-START-->
  <table name="tb_oa_product_type">
    <column>product_type_id</column>
    <column>version</column>
    <column>name</column>
    <column>display_no</column>
    <column>node_level</column>
    <column>parent_id</column>
    <column>create_by</column>
    <column>create_date</column>
    <column>modify_by</column>
    <column>modify_date</column>
    <row>
      <value>1</value>
      <value>0</value>
      <value>计算机</value>
      <null/>
      <null/>
      <null/>
      <null/>
      <null/>
      <null/>
      <null/>
    </row>
    <row>
      <value>2</value>
      <value>0</value>
      <value>文具</value>
      <null/>
      <null/>
      <null/>
      <null/>
      <null/>
      <null/>
      <null/>
    </row>
  </table>
  <!--OaProductType-END-->
	
	
	
	
	
  <!--OaScratchpad-START-->

  <!--OaScratchpad-END-->
	
	
	
	
  <!--OaWorkFlowCheckResult-START-->

  <!--OaWorkFlowCheckResult-END-->
	
	
	
  <!--OaWorkFlowType-START-->
  <table name="tb_oa_work_flow_type">
    <column>work_flow_type_id</column>
    <column>version</column>
    <column>display_no</column>
    <column>node_level</column>
    <column>parent_id</column>
    <column>name</column>
    <column>create_by</column>
    <column>create_date</column>
    <column>modify_by</column>
    <column>modify_date</column>
    <row>
      <value>1</value>
      <value>0</value>
      <value>1</value>
      <null/>
      <value>0</value>
      <value>合同审批</value>
      <null/>
      <null/>
      <null/>
      <null/>
    </row>
    <row>
      <value>2</value>
      <value>0</value>
      <value>2</value>
      <null/>
      <value>0</value>
      <value>订单审批</value>
      <null/>
      <null/>
      <null/>
      <null/>
    </row>
    <row>
      <value>3</value>
      <value>0</value>
      <value>3</value>
      <null/>
      <value>0</value>
      <value>请假审批</value>
      <null/>
      <null/>
      <null/>
      <null/>
    </row>
  </table>
  <!--OaWorkFlowType-END-->

<table name="tb_oa_work_flow">
    <column>work_flow_id</column>
    <column>version</column>
    <column>name</column>
    <column>display_no</column>
    <column>node_level</column>
    <column>parent_id</column>
    <column>agree_flow_id</column>
    <column>dissent_flow_id</column>
    <column>is_first_point</column>
    <column>is_end_point</column>
    <column>move_type_id</column>
    <column>work_flow_type_id</column>
    <column>create_by</column>
    <column>create_date</column>
    <column>modify_by</column>
    <column>modify_date</column>
    <row>
      <value>1</value>
      <value>0</value>
      <value>业务审批1</value>
      <null/>
      <null/>
      <value>0</value>
      <value>2</value>
      <value>0</value>
      <value>1</value>
      <value>0</value>
      <null/>
      <value>1</value>
      <null/>
      <null/>
      <null/>
      <null/>
    </row>
    <row>
      <value>2</value>
      <value>0</value>
      <value>财务审批1</value>
      <null/>
      <null/>
      <value>1</value>
      <value>3</value>
      <value>1</value>
      <value>0</value>
      <value>0</value>
      <null/>
      <value>1</value>
      <null/>
      <null/>
      <null/>
      <null/>
    </row>
    <row>
      <value>3</value>
      <value>0</value>
      <value>主任审批1</value>
      <null/>
      <null/>
      <value>2</value>
      <value>0</value>
      <value>2</value>
      <value>0</value>
      <value>1</value>
      <null/>
      <value>1</value>
      <null/>
      <null/>
      <null/>
      <null/>
    </row>
    <row>
      <value>4</value>
      <value>0</value>
      <value>业务部审批</value>
      <null/>
      <null/>
      <value>0</value>
      <value>5</value>
      <value>0</value>
      <value>1</value>
      <value>0</value>
      <null/>
      <value>2</value>
      <null/>
      <null/>
      <null/>
      <null/>
    </row>
    <row>
      <value>5</value>
      <value>0</value>
      <value>财务部审批</value>
      <null/>
      <null/>
      <value>4</value>
      <value>6</value>
      <value>4</value>
      <value>0</value>
      <value>0</value>
      <null/>
      <value>2</value>
      <null/>
      <null/>
      <null/>
      <null/>
    </row>
    <row>
      <value>6</value>
      <value>0</value>
      <value>主任审批</value>
      <null/>
      <null/>
      <value>5</value>
      <value>0</value>
      <value>5</value>
      <value>0</value>
      <value>1</value>
      <null/>
      <value>2</value>
      <null/>
      <null/>
      <null/>
      <null/>
    </row>
  </table>			

	
  <!--SysEventType-START-->
 <table name="tb_sys_event_type">
    <column>enent_type_id</column>
    <column>version</column>
    <column>name</column>
    <column>value</column>
    <column>create_by</column>
    <column>create_date</column>
    <column>modify_by</column>
    <column>modify_date</column>
    <row>
      <value>1</value>
      <value>0</value>
      <value>催款提示</value>
      <value>1</value>
      <null/>
      <null/>
      <null/>
      <null/>
    </row>
    <row>
      <value>2</value>
      <value>0</value>
      <value>磁带入库提示</value>
      <value>2</value>
      <null/>
      <null/>
      <null/>
      <null/>
    </row>
    <row>
      <value>3</value>
      <value>0</value>
      <value>信用额提示</value>
      <value>3</value>
      <null/>
      <null/>
      <null/>
      <null/>
    </row>
    <row>
      <value>4</value>
      <value>0</value>
      <value>新上版提示</value>
      <value>4</value>
      <null/>
      <null/>
      <null/>
      <null/>
    </row>
    <row>
      <value>5</value>
      <value>0</value>
      <value>停播提示</value>
      <value>5</value>
      <null/>
      <null/>
      <null/>
      <null/>
    </row>
  </table>
  <!--SysEventType-END-->
	
	
  <!--SysEvent-START-->

  <!--SysEvent-END-->


	
	
  <!--SysPromptMode-START-->
 <table name="tb_sys_prompt_mode">
    <column>prompt_mode_id</column>
    <column>version</column>
    <column>name</column>
    <column>value</column>
    <column>create_by</column>
    <column>create_date</column>
    <column>modify_by</column>
    <column>modify_date</column>
    <row>
      <value>1</value>
      <value>0</value>
      <value>邮件</value>
      <value>1</value>
      <null/>
      <null/>
      <null/>
      <null/>
    </row>
    <row>
      <value>2</value>
      <value>0</value>
      <value>传真</value>
      <value>2</value>
      <null/>
      <null/>
      <null/>
      <null/>
    </row>
    <row>
      <value>3</value>
      <value>0</value>
      <value>短消息</value>
      <value>3</value>
      <null/>
      <null/>
      <null/>
      <null/>
    </row>
  </table>
  <!--SysPromptMode-END-->
	
	
 <table name="tb_oa_work_flow_check_result">
    <column>check_result_id</column>
    <column>version</column>
    <column>name</column>
    <column>value</column>
    <column>create_by</column>
    <column>create_date</column>
    <column>modify_by</column>
    <column>modify_date</column>
    <row>
      <value>1</value>
      <value>0</value>
      <value>同意</value>
      <null/>
      <null/>
      <null/>
      <null/>
      <null/>
    </row>
    <row>
      <value>2</value>
      <value>0</value>
      <value>不同意</value>
      <null/>
      <null/>
      <null/>
      <null/>
      <null/>
    </row>
  </table>	
	
	
  <!--OaWorkFlowCheckState-START-->

  <table name="tb_oa_work_flow_check_state">
    <column>check_state_id</column>
    <column>version</column>
    <column>name</column>
    <column>value</column>
    <column>create_by</column>
    <column>create_date</column>
    <column>modify_by</column>
    <column>modify_date</column>
    <row>
      <value>1</value>
      <value>1</value>
      <value>未审批</value>
      <value>1</value>
      <value>1</value>
      <value><![CDATA[2007-04-20 00:00:00.0]]></value>
      <value>1</value>
      <value><![CDATA[2007-04-20 00:00:00.0]]></value>
    </row>
    <row>
      <value>2</value>
      <value>1</value>
      <value>审核中</value>
      <value>2</value>
      <value>1</value>
      <value><![CDATA[2007-04-20 00:00:00.0]]></value>
      <value>1</value>
      <value><![CDATA[2007-04-20 00:00:00.0]]></value>
    </row>
    <row>
      <value>3</value>
      <value>1</value>
      <value>通过</value>
      <value>3</value>
      <value>1</value>
      <value><![CDATA[2007-04-20 00:00:00.0]]></value>
      <value>1</value>
      <value><![CDATA[2007-04-20 00:00:00.0]]></value>
    </row>
    <row>
      <value>4</value>
      <value>1</value>
      <value>被退回</value>
      <value>4</value>
      <value>1</value>
      <value><![CDATA[2007-04-20 00:00:00.0]]></value>
      <value>1</value>
      <value><![CDATA[2007-04-20 00:00:00.0]]></value>
    </row>
  </table>

  <!--OaWorkFlowCheckState-END-->
	
  <!--OaWorkFlowMoveType-START-->

  <table name='tb_oa_work_flow_move_type'>
    <column>move_type_id</column>
    <column>name</column>
    <column>value</column>
    <column>create_by</column>
    <column>create_date</column>
    <column>modify_by</column>
    <column>modify_date</column>
    <column>version</column>
    <row>
        <value>1</value>
        <value>一票通过流转下级</value>
        <value>1</value>
        <value>1</value>
        <value>2007-04-20</value>
        <value>1</value>
        <value>2007-04-20</value>
        <value>1</value>
    </row>
    <row>
        <value>2</value>
        <value>全部通过流转下级</value>
        <value>2</value>
        <value>1</value>
        <value>2007-04-20</value>
        <value>1</value>
        <value>2007-04-20</value>
        <value>1</value>
    </row>
  </table>

  <!--OaWorkFlowMoveType-END-->	
	
	
 <table name="tb_sys_user_branch">
    <column>branch_id</column>
    <column>user_id</column>
    <row>
      <value>3</value>
      <value>1</value>
    </row>
    <row>
      <value>3</value>
      <value>2</value>
    </row>
    <row>
      <value>3</value>
      <value>3</value>
    </row>
    <row>
      <value>3</value>
      <value>4</value>
    </row>
    <row>
      <value>4</value>
      <value>5</value>
    </row>
    <row>
      <value>4</value>
      <value>6</value>
    </row>
    <row>
      <value>5</value>
      <value>11</value>
    </row>
    <row>
      <value>6</value>
      <value>7</value>
    </row>
    <row>
      <value>6</value>
      <value>13</value>
    </row>
    <row>
      <value>7</value>
      <value>8</value>
    </row>
    <row>
      <value>8</value>
      <value>9</value>
    </row>
    <row>
      <value>8</value>
      <value>14</value>
    </row>
    <row>
      <value>8</value>
      <value>15</value>
    </row>
    <row>
      <value>19</value>
      <value>10</value>
    </row>
    <row>
      <value>19</value>
      <value>12</value>
    </row>
  </table>
  
	
 <table name="tb_sys_resource_role">
    <column>resource_id</column>
    <column>role_id</column>
    <row>
      <value>1</value>
      <value>1</value>
    </row>
    <row>
      <value>2</value>
      <value>1</value>
    </row>
    <row>
      <value>2</value>
      <value>3</value>
    </row>
    <row>
      <value>2</value>
      <value>4</value>
    </row>
    <row>
      <value>3</value>
      <value>1</value>
    </row>
    <row>
      <value>3</value>
      <value>4</value>
    </row>
    <row>
      <value>4</value>
      <value>2</value>
    </row>
    <row>
      <value>5</value>
      <value>1</value>
    </row>
    <row>
      <value>6</value>
      <value>1</value>
    </row>
  </table>	
	
<table name="tb_ad_resource_sort">
    <column>ad_resource_sort_id</column>
    <column>version</column>
    <column>name</column>
    <column>value</column>
    <column>create_by</column>
    <column>create_date</column>
    <column>modify_by</column>
    <column>modify_date</column>
    <column>enable</column>
    <column>memo</column>
    <row>
      <value>1</value>
      <value>0</value>
      <value>时段</value>
      <value>1</value>
      <null/>
      <null/>
      <null/>
      <null/>
      <null/>
      <null/>
    </row>
    <row>
      <value>2</value>
      <value>0</value>
      <value>套装</value>
      <value>2</value>
      <null/>
      <null/>
      <null/>
      <null/>
      <null/>
      <null/>
    </row>
  </table>
	
</dataset>